jadia_plot/__init__.py
jadia_plot/plot.py
jadia_plot-0.1.dist-info/LICENSE
jadia_plot-0.1.dist-info/METADATA
jadia_plot-0.1.dist-info/WHEEL
jadia_plot-0.1.dist-info/top_level.txt
jadia_plot-0.1.dist-info/RECORD
