Metadata-Version: 2.1
Name: jadia-plot
Version: 0.1
Summary: Plot functions for Jadia package
Author-email: Sergey Skrebnev <sergey.skrebnev@gmail.com>
Project-URL: Homepage, https://github.com/skrbnv/jadia-plot
Classifier: Programming Language :: Python :: 3
Classifier: License :: OSI Approved :: MIT License
Classifier: Operating System :: OS Independent
Requires-Python: >=3.0
License-File: LICENSE
Requires-Dist: numpy >=2.1.0
Requires-Dist: matplotlib >=3.8.0
Requires-Dist: jadia >=0.1
